testit_cli/__init__.py
testit_cli/__main__.py
testit_cli/apiclient.py
testit_cli/args_parser.py
testit_cli/configurator.py
testit_cli/converter.py
testit_cli/importer.py
testit_cli/logger.py
testit_cli/parser.py
testit_cli/service.py
testit_cli/models/__init__.py
testit_cli/models/config.py
testit_cli/models/mode.py
testit_cli/models/status.py
testit_cli/models/testcase.py
testit_cli/models/testrun.py
testit_cli-0.1.2.dist-info/LICENSE
testit_cli-0.1.2.dist-info/METADATA
testit_cli-0.1.2.dist-info/WHEEL
testit_cli-0.1.2.dist-info/entry_points.txt
testit_cli-0.1.2.dist-info/top_level.txt
testit_cli-0.1.2.dist-info/RECORD
