Metadata-Version: 2.1
Name: testit-cli
Version: 0.1.2
Summary: This tool is the command line wrapper of Test IT allowing you to upload the test results in real time to Test IT
Home-page: https://pypi.org/project/testit/
Author: Integration team
Author-email: integrations@testit.software
License: Apache-2.0
Classifier: Programming Language :: Python :: 3
Classifier: Programming Language :: Python :: 3.6
Classifier: Programming Language :: Python :: 3.7
Classifier: Programming Language :: Python :: 3.8
Classifier: Programming Language :: Python :: 3.9
License-File: LICENSE
Requires-Dist: testit-api-client (<4,>=3)
Requires-Dist: validators
Requires-Dist: tqdm
